{
    "train_batch_size": 2,
    "eval_batch_size": 50,
    "device": "cuda",
    "train_loss_type": "sports",
    "forget_sport": "basketball",
    "maintain_sport": "null",
    "model_name": "google/gemma-7b",
    "model_type": "gemma",
    "learning_rate": 0.01,
    "n_epochs": 50,
    "grad_accum_steps": 15,
    "alpha": 0.2,
    "beta": 3e-07,
    "clip_grad": 1,
    "evaluate_every": 5,
    "n_eval_iters": 5,
    "do_adversarial_evals": true,
    "do_side_effects_evals": true,
    "localization_type": "ct",
    "localization_top_p": 0.05
}